Workbook

Sheet Variance Analysis
B4: Variance Analysis with Commentary
B5: Variance Analysis of TechFlow Inc.
B6: Line Item | C6: Acutal | D6: Budget | E6: Var vs Budget ($) | F6: Var vd Budget (%) | G6: Fav/Unfav | H6: Latest Forecast | I6: Var vs Forecast ($) | J6: Var vs Forecast (%) | K6: Fav/Unfav
B8: Revenue | C8: =Assumption!C9 -> 1250000 | D8: =Assumption!D9 -> 1000000 | E8: =C8-D8 -> 250000 | F8: =E8/D8 -> 0.25 | G8: =IF(E8>0,"Favorable","Unfavorable") -> Favorable | H8: =Assumption!E9 -> 1150000 | I8: =C8-H8 -> 100000 | J8: =I8/H8 -> 0.086956522 | K8: =IF(I8>0,"Favorable","Unfavorable") -> Favorable
B9: COGS | C9: =Assumption!C10 -> 500000 | D9: =Assumption!D10 -> 400000 | E9: =C9-D9 -> 100000 | F9: =E9/D9 -> 0.25 | G9: =IF(E9<0,"Favorable","Unfavorable") -> Unfavorable | H9: =Assumption!E10 -> 460000 | I9: =C9-H9 -> 40000 | J9: =I9/H9 -> 0.086956522 | K9: =IF(I9<0,"Favorable","Unfavorable") -> Unfavorable
B10: Gross Profit | C10: =Assumption!C11 -> 750000 | D10: =Assumption!D11 -> 600000 | E10: =C10-D10 -> 150000 | F10: =E10/D10 -> 0.25 | G10: =IF(E10>0,"Favorable","Unfavorable") -> Favorable | H10: =Assumption!E11 -> 690000 | I10: =C10-H10 -> 60000 | J10: =I10/H10 -> 0.086956522 | K10: =IF(I10>0,"Favorable","Unfavorable") -> Favorable
B11: Gross Margin % | C11: =C10/C8 -> 0.6 | D11: =D10/D8 -> 0.6 | E11: =E10/E8 -> 0.6 | F11: =E11/C11 -> 1 | G11: =IF(E11>0,"Favorable","Unfavorable") -> Favorable | H11: =Assumption!E12 -> 0.6 | I11: =I10/I8 -> 0.6 | J11: =I11/H11 -> 1 | K11: =IF(I11>0,"Favorable","Unfavorable") -> Favorable
B12: Total OpEx | C12: =Assumption!C16 -> 900000 | D12: =Assumption!D16 -> 780000 | E12: =C12-D12 -> 120000 | F12: =E12/D12 -> 0.15384615 | G12: =IF(E12<0,"Favorable","Unfavorable") -> Unfavorable | H12: =Assumption!E16 -> 862500 | I12: =C12-H12 -> 37500 | J12: =I12/H12 -> 0.043478261 | K12: =IF(I12<0,"Favorable","Unfavorable") -> Unfavorable
B13: EBITDA | C13: =Assumption!C17 -> -150000 | D13: =Assumption!D17 -> -180000 | E13: =C13-D13 -> 30000 | F13: =E13/D13 -> -0.16666667 | G13: =IF(E13>0,"Favorable","Unfavorable") -> Favorable | H13: =Assumption!E17 -> -172500 | I13: =C13-H13 -> 22500 | J13: =I13/H13 -> -0.13043478 | K13: =IF(I13>0,"Favorable","Unfavorable") -> Favorable
B14: EBITDA Margin % | C14: =C13/C8 -> -0.12 | D14: =D13/D8 -> -0.18 | E14: =C14-D14 -> 0.06 | F14: =E14/D14 -> -0.33333333 | G14: =IF(E14>0,"Favorable","Unfavorable") -> Favorable | H14: =Assumption!E18 -> -0.15 | I14: =C14-H14 -> 0.03 | J14: =I14/H14 -> -0.2 | K14: =IF(I14>0,"Favorable","Unfavorable") -> Favorable
A16: # | B16: Key Variance Insights
B18: 1. Revenue Performance - FAVORABLE
B19: Revenue of $1.25M exceeded budget by $250K (25%) and beat forecast by $100K (9%).
B20: This is the most significant positive variance. The 25% beat vs budget suggests either conservative planning or strong execution.
B21: Validate sustainability before increasing expense commitments. Could be one-time factors (year-end deals, pull-forward).
B23: 2. Cost of Good Sold - UNFAVORABLE
B24: COGS of $500K exceeded budget by $100K (25%) and beat forecast by $40K (9%).
B25: COGS grew proportionally with revenue (both +25% vs budget), maintaing 60% gross margin.
B26: No action needed on COGS - the variance is due to favorable volume, not unfavorable rate
B28: 3. Operating Expenses - UNFAVORABLE
B29: Total OpEx of $900K exceeded budget by $120K (15%) and exceed forecast by $37.5K (4%).
B30: OpEx grew faster than revenue as % of revenue - Budget: 78%, Actual: 72%, an improvement but still high.
B31: This is the #1 management focus area. OpEx discipline needed to reach ptofitability.
... B48: • INTERVIEW ANGLE: Show you understand both the positive (revenue) and concerning (OpEx) elements, and can bridge to action
A50: # | B50: Materiality Analysis: What to Focus On
B51: Variance Item | C51: $Variance | D51: % Variance | E51: Materiality | F51: Priority
B53: Revenue VS Budget | C53: =E8 -> 250000 | D53: =F8 -> 0.25 | E53: High - Largest $ Variance | F53: 1- Validate drivers
B54: OpEx Vs Budget | C54: =E12 -> 120000 | D54: =F12 -> 0.15384615 | E54: High - Path to profitability | F54: 1- Control Spending
B55: COGS VS Budget | C55: =E9 -> 100000 | D55: =F9 -> 0.25 | E55: Medium - Proportional to revenue | F55: 3- Monitor only
B56: Revenue Vs Forecast | C56: =I8 -> 100000 | D56: =J8 -> 0.086956522 | E56: Medidum - Recent beat | F56: 2 - Check sustainability
B59: Action Item for Management
B60: 1. Revenue Deep-Dive: Conduct volume/price/mix analysis to understand $250K budget beat. Was it new customers, upsells, or pricing?
B61: 2. OpEx Category Review: Break down $120K OpEx overrun by department (Sales, Marketing, G&A, R&D) to identify control opportunities
B62: 3. Forecast Accuracy Check: Investigate why forecast was $150K below actual revenue. Improve forecasting process for next year
B63: 4. Profitability Roadmap: Model scenarios to reach breakeven: (A) 17% OpEx reduction or (B) 20% revenue increase with stable margins
B64: 5. COGS Scalability: While margins held at 60%, verify COGS can maintain this rate at higher volumes for next year planning
B65: 6. Monthly Variance Tracking: Implement monthly variance reviews (not just quarterly) to catch OpEx trends earlier
B66: 7. Executive Dashboard: Create one-page KPI dashboard with revenue, GM%, OpEx%, EBITDA for weekly leadership review

Sheet Assumption
B3: Task: Analyze Q4 2025 performance for TechFlow Inc.
B4: Build a Variance Analysis Table
B7: Q4 2025 Financial Data
B8: Line Item | C8: Actual | D8: Budget | E8: Latest Forecast
B9: Revenue | C9: 1250000 | D9: 1000000 | E9: 1150000
B10: Cost of Goods Sold | C10: 500000 | D10: 400000 | E10: 460000
B11: Gross Profit | C11: 750000 | D11: 600000 | E11: 690000
B12: Gross Margin % | C12: =C11/C9 -> 0.6 | D12: =D11/D9 -> 0.6 | E12: =E11/E9 -> 0.6
B13: Sales & Marketing | C13: 425000 | D13: 350000 | E13: 402500
B14: Research & Development | C14: 312500 | D14: 280000 | E14: 322000
B15: General & Administrative | C15: 162500 | D15: 150000 | E15: 138000
B16: Total Operating Expenses | C16: 900000 | D16: 780000 | E16: 862500
B17: EBITDA | C17: -150000 | D17: -180000 | E17: -172500
B18: EBITDA Margin % | C18: =C17/C9 -> -0.12 | D18: =D17/D9 -> -0.18 | E18: =E17/E9 -> -0.15
B20: Questions:
B21: 1. What is the most significant variance you see? Is it favorable or unfavorable?
B22: 2. Revenue beat budget by 25% - is this good news? What questions would you ask?
B23: 3. EBITDA improved vs budget but is still negative. What's your assessment?
B24: 4. Which variance should management focus on first? Why?
B25: 5. If you had 2 minutes with the CFO, what would you tell them about Q4?
